{"http://rdfs.org/ns/void#linkPredicate": ["http://www.w3.org/1999/02/22-rdf-syntax-ns#type", "http://www.w3.org/ns/prov#wasAttributedTo", "http://archaeonatural.cloud/ont/hasGeneticSex", "http://archaeonatural.cloud/ont/hasSourceTissueType", "http://www.w3.org/1999/02/22-rdf-syntax-ns#first", "http://archaeonatural.cloud/ont/hasGenotypePloidy", "http://www.w3.org/ns/prov#wasAssociatedWith"], "http://rdfs.org/ns/void#objectsTarget": ["http://archaeonatural.cloud/ont/"], "http://rdfs.org/ns/void#subjectsTarget": ["http://archaeonatural.cloud/poseidon/Poseidon_Demo-Dataset"], "http://rdfs.org/ns/void#triples": ["4513", "4614", "265", "17", "50", "1"], "http://www.w3.org/1999/02/22-rdf-syntax-ns#type": ["http://rdfs.org/ns/void#Linkset"], "http://www.w3.org/2000/01/rdf-schema#label": ["Linkset: Poseidon_Demo-Dataset - arno:"]}